{
  "Студенты": [
    {
      "id": "1",
      "name": "Сергей",
      "age": "25",
      "adress": "Бибирево"
    },
    {
      "id": "2",
      "name": "Анна",
      "age": "23",
      "adress": "Свиблово"
    },
    {
      "id": "3",
      "name": "Диана",
      "age": "18",
      "adress": "Ясенево"
    },
    {
      "id": "4",
      "name": "Дмитрий",
      "age": "26",
      "adress": "Пресня"
    },
    {
      "id": "5",
      "name": "Александр",
      "age": "19",
      "adress": "Выхино"
    },
    {
      "id": "6",
      "name": "Семён",
      "age": "18",
      "adress": "Солнцево"
    }
  ]
}